{
"type": "FeatureCollection",
"name": "merged",
"crs": { "type": "name", "properties": { "name": "urn:ogc:def:crs:OGC:1.3:CRS84" } },
"features": [
{ "type": "Feature", "properties": { "name": "地域学部", "_markerType": "Icon", "_iconUrl": "https://maps.gsi.go.jp/portal/sys/v4/symbols/080.png", "_iconSize": [ 20, 20 ], "_iconAnchor": [ 10, 10 ] }, "geometry": { "type": "Point", "coordinates": [ 134.174082, 35.516358 ] } },
{ "type": "Feature", "properties": { "name": "地域学部棟", "_markerType": "Icon", "_iconUrl": "https://maps.gsi.go.jp/portal/sys/v4/symbols/080.png", "_iconSize": [ 20, 20 ], "_iconAnchor": [ 10, 10 ] }, "geometry": { "type": "Point", "coordinates": [ 134.173944, 35.516323 ] } }
]
}
