{
"type": "FeatureCollection",
"name": "merged",
"crs": { "type": "name", "properties": { "name": "urn:ogc:def:crs:OGC:1.3:CRS84" } },
"features": [
{ "type": "Feature", "properties": { "name": "スタ粋跡地", "_markerType": "Icon", "_iconUrl": "https://maps.gsi.go.jp/portal/sys/v4/symbols/080.png", "_iconSize": [ 20, 20 ], "_iconAnchor": [ 10, 10 ] }, "geometry": { "type": "Point", "coordinates": [ 134.175065, 35.518044 ] } },
{ "type": "Feature", "properties": { "name": "今を生きろ", "_markerType": "Icon", "_iconUrl": "https://maps.gsi.go.jp/portal/sys/v4/symbols/080.png", "_iconSize": [ 20, 20 ], "_iconAnchor": [ 10, 10 ] }, "geometry": { "type": "Point", "coordinates": [ 134.171941, 35.51938 ] } },
{ "type": "Feature", "properties": { "name": "鹿野", "_markerType": "Icon", "_iconUrl": "https://maps.gsi.go.jp/portal/sys/v4/symbols/080.png", "_iconSize": [ 20, 20 ], "_iconAnchor": [ 10, 10 ] }, "geometry": { "type": "Point", "coordinates": [ 134.175494, 35.517403 ] } }
]
}
